{
    "from": "Laurent MICHEL <laurent.michel@astro.unistra.fr>",
    "body": "code\r\n-- \r\n---- English version:\r\n      https://www.deepl.com/\r\n\r\n---- Laurent MICHEL              Tel  (33 0) 3 68 85 24 37\r\n      Observatoire de Strasbourg  Fax  (33 0) 3 68 85 24 32\r\n      11 Rue de l'Universite      Mail laurent.michel@astro.unistra.fr\r\n      67000 Strasbourg (France)   Web  http://astro.u-strasbg.fr/~michel\r\n---\r\n",
    "in-reply-to": "none",
    "timestamp": 1590495876.0,
    "id": "<ddf9add9-db91-ef7a-61fd-4e44546f9e7a@astro.unistra.fr>",
    "references": "none",
    "subject": "SQL",
    "data": "none",
    "to": "cisternino enzo <enzo_cisternino@hotmail.fr>",
    "num": "test1",
    "maillist": "test",
    "numThread": -1,
    "attachements": {
        "text/plain__0": "U0VMRUNUICogRlJPTSB0dXRybHV0dXR1IFdIRVJFIGRpc3BsYXkgSVMgJ25pY2Un\r\n"
    },
    "date": "Tue, 26 May 2020 14:24:36 +0200"
}